cpfeed/__init__.py
cpfeed/__main__.py
cpfeed/cpf.py
cpfeed/errors.py
cpfeed-0.13.0.dist-info/LICENSE.md
cpfeed-0.13.0.dist-info/METADATA
cpfeed-0.13.0.dist-info/WHEEL
cpfeed-0.13.0.dist-info/entry_points.txt
cpfeed-0.13.0.dist-info/RECORD
