Metadata-Version: 2.3
Name: cpfeed
Version: 0.13.0
Summary: CLI to check out current prices of cryptocurrencies. Powered by CoinGecko.
Home-page: https://github.com/0xBitzz/cpfeed
License: Copyright (c)2024 Success Daudu.
Author: 0xBitzz
Author-email: successdaudu@gmail.com
Requires-Python: <4.0,>=3.9
Classifier: Development Status :: 3 - Alpha
Classifier: Intended Audience :: Developers
Classifier: Topic :: Software Development :: Build Tools
Classifier: License :: OSI Approved :: MIT License
Classifier: Programming Language :: Python :: 3
Classifier: Programming Language :: Python :: 3.9
Classifier: Programming Language :: Python :: 3.10
Classifier: Programming Language :: Python :: 3.11
Classifier: Programming Language :: Python :: 3.12
Classifier: Programming Language :: Python :: 3.13
Classifier: Programming Language :: Python :: 3 :: Only
Provides-Extra: dev
Requires-Dist: hatch (>=1.14.0,<2.0.0)
Requires-Dist: poetry (>=2.0.0,<3.0.0)
Requires-Dist: requests (>=2.32.3,<3.0.0)
Requires-Dist: twine (>=6.0.1) ; extra == "dev"
Requires-Dist: typer (>=0.15.1,<0.16.0)
Project-URL: Repository, https://github.com/0xBitzz/cpfeed.git
Project-URL: Source, https://github.com/0xBitzz/cpfeed/
